Workbook
Name Slicer_Aircraft_Type: #N/A
Name Slicer_Aircraft_Type1: #N/A

Sheet KPI
A3: Total_Ticket_Revenue | B3: Total_Cargo_Revenue | C3: Total_Sales | D3: Total_Fuel_Cost | E3: Total_Operating_Cost_INR | F3: Total_Cost_ | G3: Total_Profit_
A4: 397071412 | B4: 41230104 | C4: 438301516 | D4: 367785528 | E4: 573580230 | F4: 941365758 | G4: -503064242
A8: _Profit_Margin_% | B8: Average_Delay_In_Minutes | C8: Total_Passengers | D8: Toatl_Seats_Available
A9: -867.89027 | B9: 46.582 | C9: 63232 | D9: 17030
A11: Month With Highest Passengers
A13: Total Passengers | B13: Year | D13: Aircraft Type | E13: Total Passengers
A14: Month | B14: 2025 | D14: A321neo | E14: 28283
A15: Jul | B15: 6911

Sheet Aircraft Wise Analysis
A2: Aircraft Wise Total Factor Level | G2: Aircraft Type Wise Total Seats Available, Revenue, Cost And Profit
A4: Total flight | B4: Factor Level | G4: Aircraft Type | H4: Total Seats_Available | I4: Total Ticket_Revenue | J4: Cargo_Revenue | K4: _Total_Revenue | L4: Fuel_Cost | M4: Operating_Cost | N4: _Total_Cost | O4: _Total_Profit | P4: _Profit_Margin_%
A5: Aircraft Type | B5: High | C5: Intermediate | D5: Low | E5: Grand Total | G5: A320neo | H5: 6306 | I5: 152006103 | J5: 13936499 | K5: 165942602 | L5: 124314700 | M5: 193478573 | N5: 317793273 | O5: -151850671 | P5: -181.67585
A6: ATR72-600 | B6: 64 | C6: 105 | D6: 6 | E6: 175 | G6: A321neo | H6: 7909 | I6: 176912750 | J6: 13504477 | K6: 190417227 | L6: 116730040 | M6: 182185906 | N6: 298915946 | O6: -108498719 | P6: -108.10204
A7: A320neo | B7: 62 | C7: 107 | E7: 169 | G7: ATR72-600 | H7: 2815 | I7: 68152559 | J7: 13789128 | K7: 81941687 | L7: 126740788 | M7: 197915751 | N7: 324656539 | O7: -242714852 | P7: -578.11237
A8: A321neo | B8: 53 | C8: 101 | D8: 2 | E8: 156 | G8: Grand Total | H8: 17030 | I8: 397071412 | J8: 41230104 | K8: 438301516 | L8: 367785528 | M8: 573580230 | N8: 941365758 | O8: -503064242 | P8: -867.89027
A9: Grand Total | B9: 179 | C9: 313 | D9: 8 | E9: 500

Sheet Route Wise Analysis
D5: Route Wise Total Seats Available, Revenue, Profit Margin And Delay
A8: Route Name | B8: % Passengers | C8: Seats_Available | D8: Cargo_Revenue | E8: Ticket_Revenue | F8: Total_Revenue_ | G8: Fuel_Cost | H8: Operating_Cost | I8: Total_Cost_ | J8: _Profit_Margin_% | K8: Average_of_Delay_in_Minutes
A9: BLR-CCU | B9: 0.089005567 | C9: 1436 | D9: 3529969 | E9: 34605633 | F9: 38135602 | G9: 28760166 | H9: 43233596 | I9: 71993762 | J9: -58.244635 | K9: 53.166667
A10: Bengaluru - Calacatta | B10: 0.089005567 | C10: 1436 | D10: 3529969 | E10: 34605633 | F10: 38135602 | G10: 28760166 | H10: 43233596 | I10: 71993762 | J10: -58.244635 | K10: 53.166667
A11: BOM-HYD | B11: 0.074882971 | C11: 1173 | D11: 3364242 | E11: 29695170 | F11: 33059412 | G11: 28722191 | H11: 43715166 | I11: 72437357 | J11: -70.711433 | K11: 49.102564
A12: Bombay - Hyderabad | B12: 0.074882971 | C12: 1173 | D12: 3364242 | E12: 29695170 | F12: 33059412 | G12: 28722191 | H12: 43715166 | I12: 72437357 | J12: -70.711433 | K12: 49.102564
A13: BLR-HYD | B13: 0.089321862 | C13: 1160 | D13: 3888809 | E13: 34331932 | F13: 38220741 | G13: 31707360 | H13: 51016409 | I13: 82723769 | J13: -74.379335 | K13: 46.113636
A14: Bengaluru - Hyderabad | B14: 0.089321862 | C14: 1160 | D14: 3888809 | E14: 34331932 | F14: 38220741 | G14: 31707360 | H14: 51016409 | I14: 82723769 | J14: -74.379335 | K14: 46.113636
A15: BLR-DEL | B15: 0.12722988 | C15: 1903 | D15: 4845924 | E15: 50309486 | F15: 55155410 | G15: 46060463 | H15: 70510652 | I15: 116571115 | J15: -85.55576 | K15: 43.103448
A16: Bengaluru - Delhi | B16: 0.12722988 | C16: 1903 | D16: 4845924 | E16: 50309486 | F16: 55155410 | G16: 46060463 | H16: 70510652 | I16: 116571115 | J16: -85.55576 | K16: 43.103448
A17: DEL-BOM | B17: 0.081762399 | C17: 1382 | D17: 3432413 | E17: 31250243 | F17: 34682656 | G17: 32041245 | H17: 49548656 | I17: 81589901 | J17: -86.717027 | K17: 48.095238
A18: Delhi - Bombay | B18: 0.081762399 | C18: 1382 | D18: 3432413 | E18: 31250243 | F18: 34682656 | G18: 32041245 | H18: 49548656 | I18: 81589901 | J18: -86.717027 | K18: 48.095238
A19: MAA-DEL | B19: 0.11823128 | C19: 2580 | D19: 4847313 | E19: 46289478 | F19: 51136791 | G19: 39875243 | H19: 65212340 | I19: 105087583 | J19: -88.363085 | K19: 46.293103
A20: Madras - Delhi | B20: 0.11823128 | C20: 2580 | D20: 4847313 | E20: 46289478 | F20: 51136791 | G20: 39875243 | H20: 65212340 | I20: 105087583 | J20: -88.363085 | K20: 46.293103
... A29: Grand Total | B29: 1 | C29: 17030 | D29: 41230104 | E29: 397071412 | F29: 438301516 | G29: 367785528 | H29: 573580230 | I29: 941365758 | J29: -867.89027 | K29: 46.582

Sheet MOM Trend Analysis
E4: Month On Month Trend Analysis
B7: Year
B8: 2025
A9: Month | B9: _Passengers | C9: Passengers Growth % | D9: Seats Available | E9: Ticket_Revenue | F9: Cargo_Revenue | G9: Total Revenue | H9: Running Total Revenue % | I9: Operating_Cost | J9: Fuel_Cost | K9: _Total_Cost | L9: _Total_Profit | M9: Profit Margin_%
A10: Jan | B10: 3361 | D10: 977 | E10: 21762088 | F10: 2173071 | G10: 23935159 | H10: 0.054608889 | I10: 34355344 | J10: 22466793 | K10: 56822137 | L10: -32886978 | M10: -71.067097
A11: Feb | B11: 4990 | C11: 0.48467718 | D11: 1716 | E11: 29383696 | F11: 3382718 | G11: 32766414 | H11: 0.12936659 | I11: 45147354 | J11: 28916550 | K11: 74063904 | L11: -41297490 | M11: -69.339361
A12: Mar | B12: 4720 | C12: -0.054108216 | D12: 1080 | E12: 27853825 | F12: 2795104 | G12: 30648929 | H12: 0.19929318 | I12: 34792085 | J12: 22968123 | K12: 57760208 | L12: -27111279 | M12: -40.783918
A13: Apr | B13: 4720 | C13: 0 | D13: 1418 | E13: 31748087 | F13: 2786921 | G13: 34535008 | H13: 0.27808599 | I13: 44942928 | J13: 31036177 | K13: 75979105 | L13: -41444097 | M13: -77.167643
A14: May | B14: 5626 | C14: 0.19194915 | D14: 1420 | E14: 36119639 | F14: 4068200 | G14: 40187839 | H14: 0.36977593 | I14: 56140016 | J14: 34868682 | K14: 91008698 | L14: -50820859 | M14: -88.524095
A15: Jun | B15: 6708 | C15: 0.19232137 | D15: 1696 | E15: 44117616 | F15: 4102200 | G15: 48219816 | H15: 0.4797911 | I15: 55806917 | J15: 36186955 | K15: 91993872 | L15: -43774056 | M15: -78.65485
A16: Jul | B16: 6911 | C16: 0.030262373 | D16: 1853 | E16: 42616149 | F16: 4391326 | G16: 47007475 | H16: 0.58704027 | I16: 59750530 | J16: 38666663 | K16: 98417193 | L16: -51409718 | M16: -74.158367
A17: Aug | B17: 5831 | C17: -0.15627261 | D17: 1497 | E17: 35842050 | F17: 4242250 | G17: 40084300 | H17: 0.67849398 | I17: 53349047 | J17: 32658232 | K17: 86007279 | L17: -45922979 | M17: -80.067292
A18: Sep | B18: 6303 | C18: 0.080946664 | D18: 1489 | E18: 42569727 | F18: 4186763 | G18: 46756490 | H18: 0.78517052 | I18: 62724023 | J18: 40118784 | K18: 102842807 | L18: -56086317 | M18: -102.88516
A19: Oct | B19: 5151 | C19: -0.18277011 | D19: 1397 | E19: 30490687 | F19: 3366644 | G19: 33857331 | H19: 0.86241719 | I19: 44399044 | J19: 26802284 | K19: 71201328 | L19: -37343997 | M19: -56.010183
A20: Nov | B20: 4609 | C20: -0.10522229 | D20: 1323 | E20: 27710311 | F20: 3053459 | G20: 30763770 | H20: 0.93260579 | I20: 46084231 | J20: 30272261 | K20: 76356492 | L20: -45592722 | M20: -76.884843
A21: Dec | B21: 4302 | C21: -0.066608809 | D21: 1164 | E21: 26857537 | F21: 2681448 | G21: 29538985 | H21: 1 | I21: 36088711 | J21: 22824024 | K21: 58912735 | L21: -29373750 | M21: -52.347457
A22: Grand Total | B22: 63232 | D22: 17030 | E22: 397071412 | F22: 41230104 | G22: 438301516 | I22: 573580230 | J22: 367785528 | K22: 941365758 | L22: -503064242 | M22: -867.89027

Sheet IndiGo_Flight_Cleaned_Data
A1: Flight_ID | B1: Date | C1: Year | D1: Month | E1: Route | F1: Route Name | G1: Aircraft_Type | H1: Passengers | I1: Seat_Capacity | J1: Seats_Available | K1: Load_Factor_% | L1: Factor_Level | M1: Ticket_Revenue_INR | N1: Cargo_Revenue_INR | O1: Total_Revenue | P1: Fuel_Cost_INR | Q1: Operating_Cost_INR | R1: Total_Cost | S1: Total_Profit | T1: Profit_Margin_% | U1: Delay_Minutes | V1: On_Time | W1: Customer_Rating | X1: Satisfaction Level
A2: 6E1002 | B2: 45781 | C2: =TEXT(Table1_1[[#This Row],[Date]],"YYYY") -> 2025 | D2: =TEXT(Table1_1[[#This Row],[Date]],"mmm") -> May | E2: DEL-GOI | F2: =INDEX(IndiGo_Flight_Data!$R$2:$R$11,MATCH(Table1_1[[#This Row],[Route]],_xlfn.ANCHORARRAY(IndiGo_Flight_Data!$Q$2),0)) -> Delhi - Goa | G2: ATR72-600 | H2: 52 | I2: 78 | J2: =Table1_1[[#This Row],[Seat_Capacity]]-Table1_1[[#This Row],[Passengers]] -> 26 | K2: 66.67 | L2: {=_xlfn.IFS(Table1_1[[#This Row],[Load_Factor_%]]<60,"Low",Table1_1[[#This Row],[Load_Factor_%]]<85,"Intermediate",Table1_1[[#This Row],[Load_Factor_%]]>=85,"High")} -> Intermediate | M2: 416298 | N2: 137633 | O2: =SUM(Table1_1[[#This Row],[Ticket_Revenue_INR]:[Cargo_Revenue_INR]]) -> 553931 | P2: 553962 | Q2: 917488 | R2: =SUM(Table1_1[[#This Row],[Fuel_Cost_INR]:[Operating_Cost_INR]]) -> 1471450 | S2: =Table1_1[[#This Row],[Total_Revenue]]-Table1_1[[#This Row],[Total_Cost]] -> -917519 | T2: =(Table1_1[[#This Row],[Total_Profit]]/Table1_1[[#This Row],[Total_Revenue]]) -> -1.6563778 | U2: 32 | V2: No | W2: 4.6 | X2: {=_xlfn.IFS(Table1_1[[#This Row],[Customer_Rating]]<3,"Poor",Table1_1[[#This Row],[Customer_Rating]]<4,"Good",Table1_1[[#This Row],[Customer_Rating]]>=4,"Excellent")} -> Excellent
A3: 6E1003 | B3: 45837 | C3: =TEXT(Table1_1[[#This Row],[Date]],"YYYY") -> 2025 | D3: =TEXT(Table1_1[[#This Row],[Date]],"mmm") -> Jun | E3: BLR-HYD | F3: =INDEX(IndiGo_Flight_Data!$R$2:$R$11,MATCH(Table1_1[[#This Row],[Route]],_xlfn.ANCHORARRAY(IndiGo_Flight_Data!$Q$2),0)) -> Bengaluru - Hyderabad | G3: ATR72-600 | H3: 69 | I3: 78 | J3: =Table1_1[[#This Row],[Seat_Capacity]]-Table1_1[[#This Row],[Passengers]] -> 9 | K3: 88.46 | L3: {=_xlfn.IFS(Table1_1[[#This Row],[Load_Factor_%]]<60,"Low",Table1_1[[#This Row],[Load_Factor_%]]<85,"Intermediate",Table1_1[[#This Row],[Load_Factor_%]]>=85,"High")} -> High | M3: 433932 | N3: 123900 | O3: =SUM(Table1_1[[#This Row],[Ticket_Revenue_INR]:[Cargo_Revenue_INR]]) -> 557832 | P3: 1081206 | Q3: 1579555 | R3: =SUM(Table1_1[[#This Row],[Fuel_Cost_INR]:[Operating_Cost_INR]]) -> 2660761 | S3: =Table1_1[[#This Row],[Total_Revenue]]-Table1_1[[#This Row],[Total_Cost]] -> -2102929 | T3: =(Table1_1[[#This Row],[Total_Profit]]/Table1_1[[#This Row],[Total_Revenue]]) -> -3.769825 | U3: 51 | V3: No | W3: 4.6 | X3: {=_xlfn.IFS(Table1_1[[#This Row],[Customer_Rating]]<3,"Poor",Table1_1[[#This Row],[Customer_Rating]]<4,"Good",Table1_1[[#This Row],[Customer_Rating]]>=4,"Excellent")} -> Excellent
A4: 6E1004 | B4: 45795 | C4: =TEXT(Table1_1[[#This Row],[Date]],"YYYY") -> 2025 | D4: =TEXT(Table1_1[[#This Row],[Date]],"mmm") -> May | E4: DEL-GOI | F4: =INDEX(IndiGo_Flight_Data!$R$2:$R$11,MATCH(Table1_1[[#This Row],[Route]],_xlfn.ANCHORARRAY(IndiGo_Flight_Data!$Q$2),0)) -> Delhi - Goa | G4: A320neo | H4: 156 | I4: 180 | J4: =Table1_1[[#This Row],[Seat_Capacity]]-Table1_1[[#This Row],[Passengers]] -> 24 | K4: 86.67 | L4: {=_xlfn.IFS(Table1_1[[#This Row],[Load_Factor_%]]<60,"Low",Table1_1[[#This Row],[Load_Factor_%]]<85,"Intermediate",Table1_1[[#This Row],[Load_Factor_%]]>=85,"High")} -> High | M4: 1160664 | N4: 88975 | O4: =SUM(Table1_1[[#This Row],[Ticket_Revenue_INR]:[Cargo_Revenue_INR]]) -> 1249639 | P4: 571295 | Q4: 1181899 | R4: =SUM(Table1_1[[#This Row],[Fuel_Cost_INR]:[Operating_Cost_INR]]) -> 1753194 | S4: =Table1_1[[#This Row],[Total_Revenue]]-Table1_1[[#This Row],[Total_Cost]] -> -503555 | T4: =(Table1_1[[#This Row],[Total_Profit]]/Table1_1[[#This Row],[Total_Revenue]]) -> -0.40296037 | U4: 59 | V4: No | W4: 4 | X4: {=_xlfn.IFS(Table1_1[[#This Row],[Customer_Rating]]<3,"Poor",Table1_1[[#This Row],[Customer_Rating]]<4,"Good",Table1_1[[#This Row],[Customer_Rating]]>=4,"Excellent")} -> Excellent
A5: 6E1005 | B5: 45839 | C5: =TEXT(Table1_1[[#This Row],[Date]],"YYYY") -> 2025 | D5: =TEXT(Table1_1[[#This Row],[Date]],"mmm") -> Jul | E5: BLR-HYD | F5: =INDEX(IndiGo_Flight_Data!$R$2:$R$11,MATCH(Table1_1[[#This Row],[Route]],_xlfn.ANCHORARRAY(IndiGo_Flight_Data!$Q$2),0)) -> Bengaluru - Hyderabad | G5: A320neo | H5: 119 | I5: 180 | J5: =Table1_1[[#This Row],[Seat_Capacity]]-Table1_1[[#This Row],[Passengers]] -> 61 | K5: 66.11 | L5: {=_xlfn.IFS(Table1_1[[#This Row],[Load_Factor_%]]<60,"Low",Table1_1[[#This Row],[Load_Factor_%]]<85,"Intermediate",Table1_1[[#This Row],[Load_Factor_%]]>=85,"High")} -> Intermediate | M5: 563493 | N5: 94456 | O5: =SUM(Table1_1[[#This Row],[Ticket_Revenue_INR]:[Cargo_Revenue_INR]]) -> 657949 | P5: 667033 | Q5: 1061516 | R5: =SUM(Table1_1[[#This Row],[Fuel_Cost_INR]:[Operating_Cost_INR]]) -> 1728549 | S5: =Table1_1[[#This Row],[Total_Revenue]]-Table1_1[[#This Row],[Total_Cost]] -> -1070600 | T5: =(Table1_1[[#This Row],[Total_Profit]]/Table1_1[[#This Row],[Total_Revenue]]) -> -1.6271778 | U5: 58 | V5: No | W5: 4 | X5: {=_xlfn.IFS(Table1_1[[#This Row],[Customer_Rating]]<3,"Poor",Table1_1[[#This Row],[Customer_Rating]]<4,"Good",Table1_1[[#This Row],[Customer_Rating]]>=4,"Excellent")} -> Excellent
A6: 6E1006 | B6: 46005 | C6: =TEXT(Table1_1[[#This Row],[Date]],"YYYY") -> 2025 | D6: =TEXT(Table1_1[[#This Row],[Date]],"mmm") -> Dec | E6: CCU-DEL | F6: =INDEX(IndiGo_Flight_Data!$R$2:$R$11,MATCH(Table1_1[[#This Row],[Route]],_xlfn.ANCHORARRAY(IndiGo_Flight_Data!$Q$2),0)) -> Calacatta - Delhi | G6: A320neo | H6: 160 | I6: 180 | J6: =Table1_1[[#This Row],[Seat_Capacity]]-Table1_1[[#This Row],[Passengers]] -> 20 | K6: 88.89 | L6: {=_xlfn.IFS(Table1_1[[#This Row],[Load_Factor_%]]<60,"Low",Table1_1[[#This Row],[Load_Factor_%]]<85,"Intermediate",Table1_1[[#This Row],[Load_Factor_%]]>=85,"High")} -> High | M6: 1412044 | N6: 38174 | O6: =SUM(Table1_1[[#This Row],[Ticket_Revenue_INR]:[Cargo_Revenue_INR]]) -> 1450218 | P6: 538384 | Q6: 1144881 | R6: =SUM(Table1_1[[#This Row],[Fuel_Cost_INR]:[Operating_Cost_INR]]) -> 1683265 | S6: =Table1_1[[#This Row],[Total_Revenue]]-Table1_1[[#This Row],[Total_Cost]] -> -233047 | T6: =(Table1_1[[#This Row],[Total_Profit]]/Table1_1[[#This Row],[Total_Revenue]]) -> -0.16069791 | U6: 88 | V6: No | W6: 4.8 | X6: {=_xlfn.IFS(Table1_1[[#This Row],[Customer_Rating]]<3,"Poor",Table1_1[[#This Row],[Customer_Rating]]<4,"Good",Table1_1[[#This Row],[Customer_Rating]]>=4,"Excellent")} -> Excellent
A7: 6E1007 | B7: 45720 | C7: =TEXT(Table1_1[[#This Row],[Date]],"YYYY") -> 2025 | D7: =TEXT(Table1_1[[#This Row],[Date]],"mmm") -> Mar | E7: BLR-COK | F7: =INDEX(IndiGo_Flight_Data!$R$2:$R$11,MATCH(Table1_1[[#This Row],[Route]],_xlfn.ANCHORARRAY(IndiGo_Flight_Data!$Q$2),0)) -> Bengaluru - Cochin | G7: A320neo | H7: 120 | I7: 180 | J7: =Table1_1[[#This Row],[Seat_Capacity]]-Table1_1[[#This Row],[Passengers]] -> 60 | K7: 66.67 | L7: {=_xlfn.IFS(Table1_1[[#This Row],[Load_Factor_%]]<60,"Low",Table1_1[[#This Row],[Load_Factor_%]]<85,"Intermediate",Table1_1[[#This Row],[Load_Factor_%]]>=85,"High")} -> Intermediate | M7: 1076575 | N7: 23868 | O7: =SUM(Table1_1[[#This Row],[Ticket_Revenue_INR]:[Cargo_Revenue_INR]]) -> 1100443 | P7: 595707 | Q7: 701587 | R7: =SUM(Table1_1[[#This Row],[Fuel_Cost_INR]:[Operating_Cost_INR]]) -> 1297294 | S7: =Table1_1[[#This Row],[Total_Revenue]]-Table1_1[[#This Row],[Total_Cost]] -> -196851 | T7: =(Table1_1[[#This Row],[Total_Profit]]/Table1_1[[#This Row],[Total_Revenue]]) -> -0.17888341 | U7: 13 | V7: Yes | W7: 3.6 | X7: {=_xlfn.IFS(Table1_1[[#This Row],[Customer_Rating]]<3,"Poor",Table1_1[[#This Row],[Customer_Rating]]<4,"Good",Table1_1[[#This Row],[Customer_Rating]]>=4,"Excellent")} -> Good
A8: 6E1008 | B8: 45792 | C8: =TEXT(Table1_1[[#This Row],[Date]],"YYYY") -> 2025 | D8: =TEXT(Table1_1[[#This Row],[Date]],"mmm") -> May | E8: DEL-BOM | F8: =INDEX(IndiGo_Flight_Data!$R$2:$R$11,MATCH(Table1_1[[#This Row],[Route]],_xlfn.ANCHORARRAY(IndiGo_Flight_Data!$Q$2),0)) -> Delhi - Bombay | G8: ATR72-600 | H8: 61 | I8: 78 | J8: =Table1_1[[#This Row],[Seat_Capacity]]-Table1_1[[#This Row],[Passengers]] -> 17 | K8: 78.21 | L8: {=_xlfn.IFS(Table1_1[[#This Row],[Load_Factor_%]]<60,"Low",Table1_1[[#This Row],[Load_Factor_%]]<85,"Intermediate",Table1_1[[#This Row],[Load_Factor_%]]>=85,"High")} -> Intermediate | M8: 525482 | N8: 18066 | O8: =SUM(Table1_1[[#This Row],[Ticket_Revenue_INR]:[Cargo_Revenue_INR]]) -> 543548 | P8: 775146 | Q8: 1167203 | R8: =SUM(Table1_1[[#This Row],[Fuel_Cost_INR]:[Operating_Cost_INR]]) -> 1942349 | S8: =Table1_1[[#This Row],[Total_Revenue]]-Table1_1[[#This Row],[Total_Cost]] -> -1398801 | T8: =(Table1_1[[#This Row],[Total_Profit]]/Table1_1[[#This Row],[Total_Revenue]]) -> -2.5734636 | U8: 77 | V8: No | W8: 4.4 | X8: {=_xlfn.IFS(Table1_1[[#This Row],[Customer_Rating]]<3,"Poor",Table1_1[[#This Row],[Customer_Rating]]<4,"Good",Table1_1[[#This Row],[Customer_Rating]]>=4,"Excellent")} -> Excellent
A9: 6E1009 | B9: 45909 | C9: =TEXT(Table1_1[[#This Row],[Date]],"YYYY") -> 2025 | D9: =TEXT(Table1_1[[#This Row],[Date]],"mmm") -> Sep | E9: BLR-DEL | F9: =INDEX(IndiGo_Flight_Data!$R$2:$R$11,MATCH(Table1_1[[#This Row],[Route]],_xlfn.ANCHORARRAY(IndiGo_Flight_Data!$Q$2),0)) -> Bengaluru - Delhi | G9: ATR72-600 | H9: 58 | I9: 78 | J9: =Table1_1[[#This Row],[Seat_Capacity]]-Table1_1[[#This Row],[Passengers]] -> 20 | K9: 74.36 | L9: {=_xlfn.IFS(Table1_1[[#This Row],[Load_Factor_%]]<60,"Low",Table1_1[[#This Row],[Load_Factor_%]]<85,"Intermediate",Table1_1[[#This Row],[Load_Factor_%]]>=85,"High")} -> Intermediate | M9: 278077 | N9: 81793 | O9: =SUM(Table1_1[[#This Row],[Ticket_Revenue_INR]:[Cargo_Revenue_INR]]) -> 359870 | P9: 903917 | Q9: 1089040 | R9: =SUM(Table1_1[[#This Row],[Fuel_Cost_INR]:[Operating_Cost_INR]]) -> 1992957 | S9: =Table1_1[[#This Row],[Total_Revenue]]-Table1_1[[#This Row],[Total_Cost]] -> -1633087 | T9: =(Table1_1[[#This Row],[Total_Profit]]/Table1_1[[#This Row],[Total_Revenue]]) -> -4.5379915 | U9: 66 | V9: No | W9: 3.5 | X9: {=_xlfn.IFS(Table1_1[[#This Row],[Customer_Rating]]<3,"Poor",Table1_1[[#This Row],[Customer_Rating]]<4,"Good",Table1_1[[#This Row],[Customer_Rating]]>=4,"Excellent")} -> Good
A10: 6E1010 | B10: 45758 | C10: =TEXT(Table1_1[[#This Row],[Date]],"YYYY") -> 2025 | D10: =TEXT(Table1_1[[#This Row],[Date]],"mmm") -> Apr | E10: BOM-HYD | F10: =INDEX(IndiGo_Flight_Data!$R$2:$R$11,MATCH(Table1_1[[#This Row],[Route]],_xlfn.ANCHORARRAY(IndiGo_Flight_Data!$Q$2),0)) -> Bombay - Hyderabad | G10: A321neo | H10: 150 | I10: 232 | J10: =Table1_1[[#This Row],[Seat_Capacity]]-Table1_1[[#This Row],[Passengers]] -> 82 | K10: 64.66 | L10: {=_xlfn.IFS(Table1_1[[#This Row],[Load_Factor_%]]<60,"Low",Table1_1[[#This Row],[Load_Factor_%]]<85,"Intermediate",Table1_1[[#This Row],[Load_Factor_%]]>=85,"High")} -> Intermediate | M10: 560539 | N10: 71419 | O10: =SUM(Table1_1[[#This Row],[Ticket_Revenue_INR]:[Cargo_Revenue_INR]]) -> 631958 | P10: 326492 | Q10: 780855 | R10: =SUM(Table1_1[[#This Row],[Fuel_Cost_INR]:[Operating_Cost_INR]]) -> 1107347 | S10: =Table1_1[[#This Row],[Total_Revenue]]-Table1_1[[#This Row],[Total_Cost]] -> -475389 | T10: =(Table1_1[[#This Row],[Total_Profit]]/Table1_1[[#This Row],[Total_Revenue]]) -> -0.75224778 | U10: 28 | V10: No | W10: 4 | X10: {=_xlfn.IFS(Table1_1[[#This Row],[Customer_Rating]]<3,"Poor",Table1_1[[#This Row],[Customer_Rating]]<4,"Good",Table1_1[[#This Row],[Customer_Rating]]>=4,"Excellent")} -> Excellent
A11: 6E1011 | B11: 45828 | C11: =TEXT(Table1_1[[#This Row],[Date]],"YYYY") -> 2025 | D11: =TEXT(Table1_1[[#This Row],[Date]],"mmm") -> Jun | E11: DEL-BOM | F11: =INDEX(IndiGo_Flight_Data!$R$2:$R$11,MATCH(Table1_1[[#This Row],[Route]],_xlfn.ANCHORARRAY(IndiGo_Flight_Data!$Q$2),0)) -> Delhi - Bombay | G11: A320neo | H11: 143 | I11: 180 | J11: =Table1_1[[#This Row],[Seat_Capacity]]-Table1_1[[#This Row],[Passengers]] -> 37 | K11: 79.44 | L11: {=_xlfn.IFS(Table1_1[[#This Row],[Load_Factor_%]]<60,"Low",Table1_1[[#This Row],[Load_Factor_%]]<85,"Intermediate",Table1_1[[#This Row],[Load_Factor_%]]>=85,"High")} -> Intermediate | M11: 1199770 | N11: 47837 | O11: =SUM(Table1_1[[#This Row],[Ticket_Revenue_INR]:[Cargo_Revenue_INR]]) -> 1247607 | P11: 350273 | Q11: 569894 | R11: =SUM(Table1_1[[#This Row],[Fuel_Cost_INR]:[Operating_Cost_INR]]) -> 920167 | S11: =Table1_1[[#This Row],[Total_Revenue]]-Table1_1[[#This Row],[Total_Cost]] -> 327440 | T11: =(Table1_1[[#This Row],[Total_Profit]]/Table1_1[[#This Row],[Total_Revenue]]) -> 0.26245444 | U11: 62 | V11: No | W11: 4.5 | X11: {=_xlfn.IFS(Table1_1[[#This Row],[Customer_Rating]]<3,"Poor",Table1_1[[#This Row],[Customer_Rating]]<4,"Good",Table1_1[[#This Row],[Customer_Rating]]>=4,"Excellent")} -> Excellent
A12: 6E1012 | B12: 46008 | C12: =TEXT(Table1_1[[#This Row],[Date]],"YYYY") -> 2025 | D12: =TEXT(Table1_1[[#This Row],[Date]],"mmm") -> Dec | E12: BLR-COK | F12: =INDEX(IndiGo_Flight_Data!$R$2:$R$11,MATCH(Table1_1[[#This Row],[Route]],_xlfn.ANCHORARRAY(IndiGo_Flight_Data!$Q$2),0)) -> Bengaluru - Cochin | G12: A320neo | H12: 176 | I12: 180 | J12: =Table1_1[[#This Row],[Seat_Capacity]]-Table1_1[[#This Row],[Passengers]] -> 4 | K12: 97.78 | L12: {=_xlfn.IFS(Table1_1[[#This Row],[Load_Factor_%]]<60,"Low",Table1_1[[#This Row],[Load_Factor_%]]<85,"Intermediate",Table1_1[[#This Row],[Load_Factor_%]]>=85,"High")} -> High | M12: 1405015 | N12: 105673 | O12: =SUM(Table1_1[[#This Row],[Ticket_Revenue_INR]:[Cargo_Revenue_INR]]) -> 1510688 | P12: 627493 | Q12: 1041494 | R12: =SUM(Table1_1[[#This Row],[Fuel_Cost_INR]:[Operating_Cost_INR]]) -> 1668987 | S12: =Table1_1[[#This Row],[Total_Revenue]]-Table1_1[[#This Row],[Total_Cost]] -> -158299 | T12: =(Table1_1[[#This Row],[Total_Profit]]/Table1_1[[#This Row],[Total_Revenue]]) -> -0.10478603 | U12: 75 | V12: No | W12: 3.8 | X12: {=_xlfn.IFS(Table1_1[[#This Row],[Customer_Rating]]<3,"Poor",Table1_1[[#This Row],[Customer_Rating]]<4,"Good",Table1_1[[#This Row],[Customer_Rating]]>=4,"Excellent")} -> Good
A13: 6E1013 | B13: 45949 | C13: =TEXT(Table1_1[[#This Row],[Date]],"YYYY") -> 2025 | D13: =TEXT(Table1_1[[#This Row],[Date]],"mmm") -> Oct | E13: BLR-COK | F13: =INDEX(IndiGo_Flight_Data!$R$2:$R$11,MATCH(Table1_1[[#This Row],[Route]],_xlfn.ANCHORARRAY(IndiGo_Flight_Data!$Q$2),0)) -> Bengaluru - Cochin | G13: A320neo | H13: 143 | I13: 180 | J13: =Table1_1[[#This Row],[Seat_Capacity]]-Table1_1[[#This Row],[Passengers]] -> 37 | K13: 79.44 | L13: {=_xlfn.IFS(Table1_1[[#This Row],[Load_Factor_%]]<60,"Low",Table1_1[[#This Row],[Load_Factor_%]]<85,"Intermediate",Table1_1[[#This Row],[Load_Factor_%]]>=85,"High")} -> Intermediate | M13: 864445 | N13: 19002 | O13: =SUM(Table1_1[[#This Row],[Ticket_Revenue_INR]:[Cargo_Revenue_INR]]) -> 883447 | P13: 452383 | Q13: 869213 | R13: =SUM(Table1_1[[#This Row],[Fuel_Cost_INR]:[Operating_Cost_INR]]) -> 1321596 | S13: =Table1_1[[#This Row],[Total_Revenue]]-Table1_1[[#This Row],[Total_Cost]] -> -438149 | T13: =(Table1_1[[#This Row],[Total_Profit]]/Table1_1[[#This Row],[Total_Revenue]]) -> -0.49595392 | U13: 68 | V13: No | W13: 4.5 | X13: {=_xlfn.IFS(Table1_1[[#This Row],[Customer_Rating]]<3,"Poor",Table1_1[[#This Row],[Customer_Rating]]<4,"Good",Table1_1[[#This Row],[Customer_Rating]]>=4,"Excellent")} -> Excellent
... A501: 6E1501 | B501: 45842 | C501: =TEXT(Table1_1[[#This Row],[Date]],"YYYY") -> 2025 | D501: =TEXT(Table1_1[[#This Row],[Date]],"mmm") -> Jul | E501: BLR-CCU | F501: =INDEX(IndiGo_Flight_Data!$R$2:$R$11,MATCH(Table1_1[[#This Row],[Route]],_xlfn.ANCHORARRAY(IndiGo_Flight_Data!$Q$2),0)) -> Bengaluru - Calacatta | G501: A321neo | H501: 195 | I501: 232 | J501: =Table1_1[[#This Row],[Seat_Capacity]]-Table1_1[[#This Row],[Passengers]] -> 37 | K501: 84.05 | L501: {=_xlfn.IFS(Table1_1[[#This Row],[Load_Factor_%]]<60,"Low",Table1_1[[#This Row],[Load_Factor_%]]<85,"Intermediate",Table1_1[[#This Row],[Load_Factor_%]]>=85,"High")} -> Intermediate | M501: 719344 | N501: 133232 | O501: =SUM(Table1_1[[#This Row],[Ticket_Revenue_INR]:[Cargo_Revenue_INR]]) -> 852576 | P501: 1018547 | Q501: 1202464 | R501: =SUM(Table1_1[[#This Row],[Fuel_Cost_INR]:[Operating_Cost_INR]]) -> 2221011 | S501: =Table1_1[[#This Row],[Total_Revenue]]-Table1_1[[#This Row],[Total_Cost]] -> -1368435 | T501: =(Table1_1[[#This Row],[Total_Profit]]/Table1_1[[#This Row],[Total_Revenue]]) -> -1.6050593 | U501: 11 | V501: Yes | W501: 4.3 | X501: {=_xlfn.IFS(Table1_1[[#This Row],[Customer_Rating]]<3,"Poor",Table1_1[[#This Row],[Customer_Rating]]<4,"Good",Table1_1[[#This Row],[Customer_Rating]]>=4,"Excellent")} -> Excellent

Sheet IndiGo_Flight_Data
A1: Flight_ID | B1: Date | C1: Route | D1: Aircraft_Type | E1: Passengers | F1: Seat_Capacity | G1: Load_Factor_% | H1: Ticket_Revenue_INR | I1: Cargo_Revenue_INR | J1: Fuel_Cost_INR | K1: Operating_Cost_INR | L1: Delay_Minutes | M1: On_Time | N1: Customer_Rating | Q1: Route | R1: Route Name
A2: 6E1002 | B2: 2025-05-04 | C2: DEL-GOI | D2: ATR72-600 | E2: 52 | F2: 78 | G2: 66.67 | H2: 416298 | I2: 137633 | J2: 553962 | K2: 917488 | L2: 32 | M2: No | N2: 4.6 | Q2: {=_xlfn.UNIQUE(Table1_1[Route])} -> DEL-GOI | R2: Delhi - Goa
A3: 6E1003 | B3: 2025-06-29 | C3: BLR-HYD | D3: ATR72-600 | E3: 69 | F3: 78 | G3: 88.46 | H3: 433932 | I3: 123900 | J3: 1081206 | K3: 1579555 | L3: 51 | M3: No | N3: 4.6 | Q3: BLR-HYD | R3: Bengaluru - Hyderabad
A4: 6E1004 | B4: 2025-05-18 | C4: DEL-GOI | D4: A320neo | E4: 156 | F4: 180 | G4: 86.67 | H4: 1160664 | I4: 88975 | J4: 571295 | K4: 1181899 | L4: 59 | M4: No | N4: 4 | Q4: CCU-DEL | R4: Calacatta - Delhi
A5: 6E1005 | B5: 2025-07-01 | C5: BLR-HYD | D5: A320neo | E5: 119 | F5: 180 | G5: 66.11 | H5: 563493 | I5: 94456 | J5: 667033 | K5: 1061516 | L5: 58 | M5: No | N5: 4 | Q5: BLR-COK | R5: Bengaluru - Cochin
A6: 6E1006 | B6: 2025-12-14 | C6: CCU-DEL | D6: A320neo | E6: 160 | F6: 180 | G6: 88.89 | H6: 1412044 | I6: 38174 | J6: 538384 | K6: 1144881 | L6: 88 | M6: No | N6: 4.8 | Q6: DEL-BOM | R6: Delhi - Bombay
A7: 6E1007 | B7: 2025-03-04 | C7: BLR-COK | D7: A320neo | E7: 120 | F7: 180 | G7: 66.67 | H7: 1076575 | I7: 23868 | J7: 595707 | K7: 701587 | L7: 13 | M7: Yes | N7: 3.6 | Q7: BLR-DEL | R7: Bengaluru - Delhi
A8: 6E1008 | B8: 2025-05-15 | C8: DEL-BOM | D8: ATR72-600 | E8: 61 | F8: 78 | G8: 78.21 | H8: 525482 | I8: 18066 | J8: 775146 | K8: 1167203 | L8: 77 | M8: No | N8: 4.4 | Q8: BOM-HYD | R8: Bombay - Hyderabad
A9: 6E1009 | B9: 2025-09-09 | C9: BLR-DEL | D9: ATR72-600 | E9: 58 | F9: 78 | G9: 74.36 | H9: 278077 | I9: 81793 | J9: 903917 | K9: 1089040 | L9: 66 | M9: No | N9: 3.5 | Q9: BLR-BOM | R9: Bengaluru - Bombay
A10: 6E1010 | B10: 2025-04-11 | C10: BOM-HYD | D10: A321neo | E10: 150 | F10: 232 | G10: 64.66 | H10: 560539 | I10: 71419 | J10: 326492 | K10: 780855 | L10: 28 | M10: No | N10: 4 | Q10: MAA-DEL | R10: Madras - Delhi
A11: 6E1011 | B11: 2025-06-20 | C11: DEL-BOM | D11: A320neo | E11: 143 | F11: 180 | G11: 79.44 | H11: 1199770 | I11: 47837 | J11: 350273 | K11: 569894 | L11: 62 | M11: No | N11: 4.5 | Q11: BLR-CCU | R11: Bengaluru - Calacatta
A12: 6E1012 | B12: 2025-12-17 | C12: BLR-COK | D12: A320neo | E12: 176 | F12: 180 | G12: 97.78 | H12: 1405015 | I12: 105673 | J12: 627493 | K12: 1041494 | L12: 75 | M12: No | N12: 3.8
A13: 6E1013 | B13: 2025-10-19 | C13: BLR-COK | D13: A320neo | E13: 143 | F13: 180 | G13: 79.44 | H13: 864445 | I13: 19002 | J13: 452383 | K13: 869213 | L13: 68 | M13: No | N13: 4.5
A14: 6E1014 | B14: 2025-05-15 | C14: BLR-COK | D14: A320neo | E14: 108 | F14: 180 | G14: 60 | H14: 680336 | I14: 128190 | J14: 488979 | K14: 957702 | L14: 8 | M14: Yes | N14: 4
A15: 6E1015 | B15: 2025-07-04 | C15: BLR-HYD | D15: ATR72-600 | E15: 62 | F15: 78 | G15: 79.49 | H15: 252119 | I15: 57564 | J15: 976509 | K15: 1250413 | L15: 60 | M15: No | N15: 3.2
A16: 6E1016 | B16: 2025-11-16 | C16: DEL-GOI | D16: ATR72-600 | E16: 60 | F16: 78 | G16: 76.92 | H16: 358179 | I16: 119557 | J16: 1102755 | K16: 1329274 | L16: 23 | M16: No | N16: 3.4
A17: 6E1017 | B17: 2025-11-04 | C17: BLR-DEL | D17: ATR72-600 | E17: 46 | F17: 78 | G17: 58.97 | H17: 229070 | I17: 98425 | J17: 695113 | K17: 1033032 | L17: 36 | M17: No | N17: 4.6
A18: 6E1018 | B18: 2025-05-19 | C18: BLR-BOM | D18: A321neo | E18: 207 | F18: 232 | G18: 89.22 | H18: 1517723 | I18: 38841 | J18: 395556 | K18: 657365 | L18: 6 | M18: Yes | N18: 3.5
A19: 6E1019 | B19: 2025-07-06 | C19: BLR-DEL | D19: A321neo | E19: 220 | F19: 232 | G19: 94.83 | H19: 1022492 | I19: 128868 | J19: 1199424 | K19: 1611052 | L19: 12 | M19: Yes | N19: 4.5
A20: 6E1020 | B20: 2025-09-13 | C20: BLR-BOM | D20: A321neo | E20: 206 | F20: 232 | G20: 88.79 | H20: 1663426 | I20: 92596 | J20: 699917 | K20: 1314679 | L20: 27 | M20: No | N20: 4.4
A21: 6E1021 | B21: 2025-08-24 | C21: BLR-HYD | D21: A321neo | E21: 167 | F21: 232 | G21: 71.98 | H21: 597979 | I21: 108783 | J21: 538692 | K21: 1122269 | L21: 8 | M21: Yes | N21: 4.3
A22: 6E1022 | B22: 2025-09-20 | C22: DEL-BOM | D22: A320neo | E22: 127 | F22: 180 | G22: 70.56 | H22: 847210 | I22: 70310 | J22: 889914 | K22: 1148596 | L22: 4 | M22: Yes | N22: 4.3
A23: 6E1023 | B23: 2025-10-03 | C23: BOM-HYD | D23: A320neo | E23: 146 | F23: 180 | G23: 81.11 | H23: 989633 | I23: 97579 | J23: 381248 | K23: 595995 | L23: 66 | M23: No | N23: 4.5
... A501: 6E1501 | B501: 2025-07-04 | C501: BLR-CCU | D501: A321neo | E501: 195 | F501: 232 | G501: 84.05 | H501: 719344 | I501: 133232 | J501: 1018547 | K501: 1202464 | L501: 11 | M501: Yes | N501: 4.3
